Metadata-Version: 1.0
Name: FuXi
Version: 1.4.1.production
Summary: An OWL / N3-based in-memory, logic reasoning system for RDF
Home-page: http://code.google.com/p/python-dlp/wiki/FuXi
Author: Chime Ogbuji
Author-email: chimezie@gmail.com
License: Apache
Keywords: python logic owl rdf dlp n3 rule reasoner
Platform: UNKNOWN
